odoo/addons/purchase_product_pack/README.rst
odoo/addons/purchase_product_pack/__init__.py
odoo/addons/purchase_product_pack/__manifest__.py
odoo/addons/purchase_product_pack/i18n/it.po
odoo/addons/purchase_product_pack/i18n/pt.po
odoo/addons/purchase_product_pack/i18n/purchase_product_pack.pot
odoo/addons/purchase_product_pack/models/__init__.py
odoo/addons/purchase_product_pack/models/product_pack_line.py
odoo/addons/purchase_product_pack/models/product_product.py
odoo/addons/purchase_product_pack/models/purchase_order.py
odoo/addons/purchase_product_pack/models/purchase_order_line.py
odoo/addons/purchase_product_pack/readme/CONTRIBUTORS.md
odoo/addons/purchase_product_pack/readme/CREDITS.md
odoo/addons/purchase_product_pack/readme/DESCRIPTION.md
odoo/addons/purchase_product_pack/readme/USAGE.md
odoo/addons/purchase_product_pack/security/ir.model.access.csv
odoo/addons/purchase_product_pack/static/description/icon.png
odoo/addons/purchase_product_pack/static/description/index.html
odoo/addons/purchase_product_pack/tests/__init__.py
odoo/addons/purchase_product_pack/tests/test_purchase_product_pack.py
odoo/addons/purchase_product_pack/views/product_pack_line_views.xml
odoo_addon_purchase_product_pack-18.0.1.0.0.2.dist-info/METADATA
odoo_addon_purchase_product_pack-18.0.1.0.0.2.dist-info/WHEEL
odoo_addon_purchase_product_pack-18.0.1.0.0.2.dist-info/top_level.txt
odoo_addon_purchase_product_pack-18.0.1.0.0.2.dist-info/RECORD
