Metadata-Version: 2.1
Name: odoo-addon-purchase_product_pack
Version: 18.0.1.0.0.2
Requires-Python: >=3.10
Requires-Dist: odoo-addon-product_pack==18.0.*
Requires-Dist: odoo==18.0.*
Summary: This module allows you to buy product packs
Home-page: https://github.com/OCA/product-pack
License: AGPL-3
Author: Camptocamp, Odoo Community Association (OCA)
Author-email: support@odoo-community.org
Classifier: Programming Language :: Python
Classifier: Framework :: Odoo
Classifier: Framework :: Odoo :: 18.0
Classifier: License :: OSI Approved :: GNU Affero General Public License v3
